pyMRA/DataLoader.py
pyMRA/MRANode.py
pyMRA/MRATools.py
pyMRA/MRATree.py
pyMRA/__init__.py
pyMRA/bbNode.py
pyMRA/data/large/Exp_Theta0.1_X100_Y100.csv
pyMRA/data/large/locs.npy
pyMRA/data/large/y.npy
pyMRA/data/large/y_obs.npy
pyMRA/data/small/Exp_Theta0.1_X10_Y10.csv
pyMRA/data/small/locs.npy
pyMRA/data/small/y.npy
pyMRA/data/small/y_obs.npy
pyMRA/multiprocess/__init__.py
pyMRA/multiprocess/basic-multiprocessing.py
pyMRA/multiprocess/example.py
pyMRA/multiprocess/parutils.py
pyMRA/multiprocess/test-multiprocess.py
pyMRA/multiprocess/test-par-children.py
pyMRA/multiprocess/testMPI.py
pyMRA/tests/__init__.py
pyMRA/tests/test-MRA-data.py
pyMRA/tests/test-MRA.py
pyMRA/tests/test-circ-cov.py
pyMRA/tests/test-row-order.py
pyMRA/tests/unit-tests.py
pyMRA-0.8.1.dist-info/DESCRIPTION.rst
pyMRA-0.8.1.dist-info/METADATA
pyMRA-0.8.1.dist-info/RECORD
pyMRA-0.8.1.dist-info/WHEEL
pyMRA-0.8.1.dist-info/metadata.json
pyMRA-0.8.1.dist-info/top_level.txt
