Metadata-Version: 2.0
Name: pyMRA
Version: 0.8.1
Summary: Multi-resolution approximation for spatial Gaussian processes
Home-page: https://github.com/marcinjurek/pyMRA
Author: Marcin Jurek
Author-email: marcinjurek1988@gmail.com
License: UNKNOWN
Keywords: Gaussian process,multi-resolution,sparse,approximation,spatial,statistics
Platform: UNKNOWN
Requires-Dist: numpy
Requires-Dist: matplotlib
Requires-Dist: scipy
Requires-Dist: numpy-indexed
Requires-Dist: sklearn
Requires-Dist: pathos
